ajax_select/LICENSE.txt
ajax_select/__init__.py
ajax_select/admin.py
ajax_select/apps.py
ajax_select/fields.py
ajax_select/helpers.py
ajax_select/lookup_channel.py
ajax_select/registry.py
ajax_select/static/ajax_select/css/ajax_select.css
ajax_select/static/ajax_select/images/loading-indicator.gif
ajax_select/static/ajax_select/js/ajax_select.js
ajax_select/static/ajax_select/vendor/jquery-3.7.1.min.js
ajax_select/static/ajax_select/vendor/jquery-ui-1.13.2/AUTHORS.txt
ajax_select/static/ajax_select/vendor/jquery-ui-1.13.2/LICENSE.txt
ajax_select/static/ajax_select/vendor/jquery-ui-1.13.2/external/jquery/jquery.js
ajax_select/static/ajax_select/vendor/jquery-ui-1.13.2/images/ui-icons_444444_256x240.png
ajax_select/static/ajax_select/vendor/jquery-ui-1.13.2/images/ui-icons_555555_256x240.png
ajax_select/static/ajax_select/vendor/jquery-ui-1.13.2/images/ui-icons_777620_256x240.png
ajax_select/static/ajax_select/vendor/jquery-ui-1.13.2/images/ui-icons_777777_256x240.png
ajax_select/static/ajax_select/vendor/jquery-ui-1.13.2/images/ui-icons_cc0000_256x240.png
ajax_select/static/ajax_select/vendor/jquery-ui-1.13.2/images/ui-icons_ffffff_256x240.png
ajax_select/static/ajax_select/vendor/jquery-ui-1.13.2/index.html
ajax_select/static/ajax_select/vendor/jquery-ui-1.13.2/jquery-ui.css
ajax_select/static/ajax_select/vendor/jquery-ui-1.13.2/jquery-ui.js
ajax_select/static/ajax_select/vendor/jquery-ui-1.13.2/jquery-ui.min.css
ajax_select/static/ajax_select/vendor/jquery-ui-1.13.2/jquery-ui.min.js
ajax_select/static/ajax_select/vendor/jquery-ui-1.13.2/jquery-ui.structure.css
ajax_select/static/ajax_select/vendor/jquery-ui-1.13.2/jquery-ui.structure.min.css
ajax_select/static/ajax_select/vendor/jquery-ui-1.13.2/jquery-ui.theme.css
ajax_select/static/ajax_select/vendor/jquery-ui-1.13.2/jquery-ui.theme.min.css
ajax_select/static/ajax_select/vendor/jquery-ui-1.13.2/package.json
ajax_select/templates/ajax_select/autocomplete.html
django_ajax_selects-3.0.2.dist-info/LICENSE
django_ajax_selects-3.0.2.dist-info/METADATA
django_ajax_selects-3.0.2.dist-info/WHEEL
django_ajax_selects-3.0.2.dist-info/RECORD
