Metadata-Version: 2.1
Name: django-ajax-selects
Version: 3.0.2
Summary: Edit ForeignKey, ManyToManyField and CharField in Django Admin using jQuery UI AutoComplete.
Home-page: https://github.com/crucialfelix/django-ajax-selects
License: MIT, GPL
Author: Chris Sattinger
Author-email: crucialfelix@gmail.com
Requires-Python: >=3.10,<4.0
Classifier: Development Status :: 5 - Production/Stable
Classifier: Environment :: Web Environment
Classifier: Framework :: Django
Classifier: Intended Audience :: Developers
Classifier: License :: OSI Approved :: MIT License
Classifier: License :: Other/Proprietary License
Classifier: Operating System :: OS Independent
Classifier: Programming Language :: Python
Classifier: Programming Language :: Python :: 3
Classifier: Programming Language :: Python :: 3.10
Classifier: Programming Language :: Python :: 3.11
Classifier: Programming Language :: Python :: 3.12
Classifier: Topic :: Software Development :: Libraries :: Python Modules
Classifier: Topic :: Software Development :: User Interfaces
Requires-Dist: Django (>=3.2)
Project-URL: Documentation, https://django-ajax-selects.readthedocs.io/en/latest/
Project-URL: Repository, https://github.com/crucialfelix/django-ajax-selects
